Workbook

Sheet Executive Dashboard
A1: 🏪 E-COMMERCE SALES PERFORMANCE DASHBOARD | FY 2024
A2: Prepared by: Omer Abdalla | Data Analyst & Banking Professional | June 2026
A4: Total Revenue | C4: Net Revenue | E4: Gross Profit | G4: GP Margin % | I4: Total Units Sold | K4: Total Returns
A5: ='Monthly Summary'!C17 -> 13303526 | C5: ='Monthly Summary'!H17 -> 13000787 | E5: ='Monthly Summary'!E17 -> 6268729.8 | G5: =IFERROR('Monthly Summary'!E17/'Monthly Summary'!C17,0) -> 0.47120815 | I5: ='Monthly Summary'!B17 -> 99864 | K5: ='Monthly Summary'!G17 -> 2357
A8: TOP CATEGORIES BY REVENUE | F8: REGIONAL PERFORMANCE OVERVIEW
A9: Category | B9: Revenue ($) | C9: GP ($) | D9: Margin % | F9: Region | G9: Revenue ($) | H9: GP ($) | I9: Margin %
A10: ='Category Analysis'!A5 -> Electronics | B10: ='Category Analysis'!C5 -> 2011117.6 | C10: ='Category Analysis'!D5 -> 951192.34 | D10: ='Category Analysis'!E5 -> 0.47296703 | F10: ='Region Analysis'!A5 -> North | G10: ='Region Analysis'!C5 -> 2603868.8 | H10: ='Region Analysis'!D5 -> 1242799 | I10: ='Region Analysis'!E5 -> 0.47728941
A11: ='Category Analysis'!A6 -> Clothing | B11: ='Category Analysis'!C6 -> 2351492.5 | C11: ='Category Analysis'!D6 -> 1120352.7 | D11: ='Category Analysis'!E6 -> 0.47644326 | F11: ='Region Analysis'!A6 -> South | G11: ='Region Analysis'!C6 -> 2512433 | H11: ='Region Analysis'!D6 -> 1187111.8 | I11: ='Region Analysis'!E6 -> 0.4724949
A12: ='Category Analysis'!A7 -> Home & Garden | B12: ='Category Analysis'!C7 -> 1979342.1 | C12: ='Category Analysis'!D7 -> 919029.55 | D12: ='Category Analysis'!E7 -> 0.46431063 | F12: ='Region Analysis'!A7 -> East | G12: ='Region Analysis'!C7 -> 3028926.5 | H12: ='Region Analysis'!D7 -> 1402507.1 | I12: ='Region Analysis'!E7 -> 0.46303768
A13: ='Category Analysis'!A8 -> Sports | B13: ='Category Analysis'!C8 -> 2521901.5 | C13: ='Category Analysis'!D8 -> 1199146.4 | D13: ='Category Analysis'!E8 -> 0.47549294 | F13: ='Region Analysis'!A8 -> West | G13: ='Region Analysis'!C8 -> 2318744.8 | H13: ='Region Analysis'!D8 -> 1106432.4 | I13: ='Region Analysis'!E8 -> 0.47716871
A14: ='Category Analysis'!A9 -> Beauty | B14: ='Category Analysis'!C9 -> 2200077 | C14: ='Category Analysis'!D9 -> 1024688.7 | D14: ='Category Analysis'!E9 -> 0.46575129 | F14: ='Region Analysis'!A9 -> Central | G14: ='Region Analysis'!C9 -> 2839552.6 | H14: ='Region Analysis'!D9 -> 1329879.4 | I14: ='Region Analysis'!E9 -> 0.46834119
A15: ='Category Analysis'!A10 -> Books | B15: ='Category Analysis'!C10 -> 2239595.1 | C15: ='Category Analysis'!D10 -> 1054320.1 | D15: ='Category Analysis'!E10 -> 0.47076372
A30: © 2026 Omer Abdalla | Data Analysis & Banking Professional | github.com/3mor9411

Sheet Sales Data
A1: Month | B1: Category | C1: Region | D1: Units Sold | E1: Unit Price ($) | F1: Revenue ($) | G1: COGS ($) | H1: Gross Profit ($) | I1: Returns | J1: Net Revenue ($)
A2: Jan | B2: Electronics | C2: North | D2: 377 | E2: 36.72 | F2: =D2*E2 -> 13843.44 | G2: 8103.78 | H2: =F2-G2 -> 5739.66 | I2: 7 | J2: =F2-I2*E2 -> 13586.4
A3: Jan | B3: Electronics | C3: South | D3: 164 | E3: 43.49 | F3: =D3*E3 -> 7132.36 | G3: 3035.7 | H3: =F3-G3 -> 4096.66 | I3: 8 | J3: =F3-I3*E3 -> 6784.44
A4: Jan | B4: Electronics | C4: East | D4: 94 | E4: 151.72 | F4: =D4*E4 -> 14261.68 | G4: 5817.99 | H4: =F4-G4 -> 8443.69 | I4: 0 | J4: =F4-I4*E4 -> 14261.68
A5: Jan | B5: Electronics | C5: West | D5: 161 | E5: 65.84 | F5: =D5*E5 -> 10600.24 | G5: 5835.48 | H5: =F5-G5 -> 4764.76 | I5: 8 | J5: =F5-I5*E5 -> 10073.52
A6: Jan | B6: Electronics | C6: Central | D6: 151 | E6: 181.84 | F6: =D6*E6 -> 27457.84 | G6: 15797.35 | H6: =F6-G6 -> 11660.49 | I6: 6 | J6: =F6-I6*E6 -> 26366.8
A7: Jan | B7: Clothing | C7: North | D7: 162 | E7: 117.81 | F7: =D7*E7 -> 19085.22 | G7: 8961.42 | H7: =F7-G7 -> 10123.8 | I7: 0 | J7: =F7-I7*E7 -> 19085.22
A8: Jan | B8: Clothing | C8: South | D8: 438 | E8: 203.4 | F8: =D8*E8 -> 89089.2 | G8: 51184.85 | H8: =F8-G8 -> 37904.35 | I8: 10 | J8: =F8-I8*E8 -> 87055.2
A9: Jan | B9: Clothing | C9: East | D9: 192 | E9: 47.32 | F9: =D9*E9 -> 9085.44 | G9: 5808.35 | H9: =F9-G9 -> 3277.09 | I9: 5 | J9: =F9-I9*E9 -> 8848.84
A10: Jan | B10: Clothing | C10: West | D10: 102 | E10: 32.26 | F10: =D10*E10 -> 3290.52 | G10: 1395.77 | H10: =F10-G10 -> 1894.75 | I10: 2 | J10: =F10-I10*E10 -> 3226
A11: Jan | B11: Clothing | C11: Central | D11: 359 | E11: 73.49 | F11: =D11*E11 -> 26382.91 | G11: 10839.75 | H11: =F11-G11 -> 15543.16 | I11: 14 | J11: =F11-I11*E11 -> 25354.05
A12: Jan | B12: Home & Garden | C12: North | D12: 324 | E12: 39.96 | F12: =D12*E12 -> 12947.04 | G12: 8164.06 | H12: =F12-G12 -> 4782.98 | I12: 2 | J12: =F12-I12*E12 -> 12867.12
A13: Jan | B13: Home & Garden | C13: South | D13: 332 | E13: 80.36 | F13: =D13*E13 -> 26679.52 | G13: 14864.76 | H13: =F13-G13 -> 11814.76 | I13: 11 | J13: =F13-I13*E13 -> 25795.56
... A361: Dec | B361: Books | C361: Central | D361: 198 | E361: 37.64 | F361: =D361*E361 -> 7452.72 | G361: 3019.95 | H361: =F361-G361 -> 4432.77 | I361: 5 | J361: =F361-I361*E361 -> 7264.52

Sheet Monthly Summary
A1: 📊 MONTHLY SALES SUMMARY — 2024
A2: E-Commerce Sales Performance Dashboard | Prepared by: Omer Abdalla
A4: Month | B4: Total Units | C4: Total Revenue ($) | D4: Total COGS ($) | E4: Gross Profit ($) | F4: GP Margin % | G4: Total Returns | H4: Net Revenue ($)
A5: Jan | B5: =SUMIF('Sales Data'!A:A,A5,'Sales Data'!D:D) -> 8425 | C5: =SUMIF('Sales Data'!A:A,A5,'Sales Data'!F:F) -> 862650.45 | D5: =SUMIF('Sales Data'!A:A,A5,'Sales Data'!G:G) -> 458778.03 | E5: =C5-D5 -> 403872.42 | F5: =IFERROR(E5/C5,0) -> 0.46817621 | G5: =SUMIF('Sales Data'!A:A,A5,'Sales Data'!I:I) -> 199 | H5: =SUMIF('Sales Data'!A:A,A5,'Sales Data'!J:J) -> 843725.79
A6: Feb | B6: =SUMIF('Sales Data'!A:A,A6,'Sales Data'!D:D) -> 7917 | C6: =SUMIF('Sales Data'!A:A,A6,'Sales Data'!F:F) -> 1044200.3 | D6: =SUMIF('Sales Data'!A:A,A6,'Sales Data'!G:G) -> 581865.81 | E6: =C6-D6 -> 462334.5 | F6: =IFERROR(E6/C6,0) -> 0.44276419 | G6: =SUMIF('Sales Data'!A:A,A6,'Sales Data'!I:I) -> 180 | H6: =SUMIF('Sales Data'!A:A,A6,'Sales Data'!J:J) -> 1021990.9
A7: Mar | B7: =SUMIF('Sales Data'!A:A,A7,'Sales Data'!D:D) -> 5873 | C7: =SUMIF('Sales Data'!A:A,A7,'Sales Data'!F:F) -> 863686.64 | D7: =SUMIF('Sales Data'!A:A,A7,'Sales Data'!G:G) -> 477925.21 | E7: =C7-D7 -> 385761.43 | F7: =IFERROR(E7/C7,0) -> 0.44664513 | G7: =SUMIF('Sales Data'!A:A,A7,'Sales Data'!I:I) -> 124 | H7: =SUMIF('Sales Data'!A:A,A7,'Sales Data'!J:J) -> 845339.24
A8: Apr | B8: =SUMIF('Sales Data'!A:A,A8,'Sales Data'!D:D) -> 8680 | C8: =SUMIF('Sales Data'!A:A,A8,'Sales Data'!F:F) -> 1028159 | D8: =SUMIF('Sales Data'!A:A,A8,'Sales Data'!G:G) -> 557657.84 | E8: =C8-D8 -> 470501.19 | F8: =IFERROR(E8/C8,0) -> 0.45761519 | G8: =SUMIF('Sales Data'!A:A,A8,'Sales Data'!I:I) -> 192 | H8: =SUMIF('Sales Data'!A:A,A8,'Sales Data'!J:J) -> 1008481.8
A9: May | B9: =SUMIF('Sales Data'!A:A,A9,'Sales Data'!D:D) -> 9628 | C9: =SUMIF('Sales Data'!A:A,A9,'Sales Data'!F:F) -> 1336522.1 | D9: =SUMIF('Sales Data'!A:A,A9,'Sales Data'!G:G) -> 716295.69 | E9: =C9-D9 -> 620226.4 | F9: =IFERROR(E9/C9,0) -> 0.46405997 | G9: =SUMIF('Sales Data'!A:A,A9,'Sales Data'!I:I) -> 237 | H9: =SUMIF('Sales Data'!A:A,A9,'Sales Data'!J:J) -> 1303942.4
A10: Jun | B10: =SUMIF('Sales Data'!A:A,A10,'Sales Data'!D:D) -> 8857 | C10: =SUMIF('Sales Data'!A:A,A10,'Sales Data'!F:F) -> 1326786 | D10: =SUMIF('Sales Data'!A:A,A10,'Sales Data'!G:G) -> 689193.27 | E10: =C10-D10 -> 637592.77 | F10: =IFERROR(E10/C10,0) -> 0.48055433 | G10: =SUMIF('Sales Data'!A:A,A10,'Sales Data'!I:I) -> 208 | H10: =SUMIF('Sales Data'!A:A,A10,'Sales Data'!J:J) -> 1296803.1
A11: Jul | B11: =SUMIF('Sales Data'!A:A,A11,'Sales Data'!D:D) -> 7001 | C11: =SUMIF('Sales Data'!A:A,A11,'Sales Data'!F:F) -> 983369.15 | D11: =SUMIF('Sales Data'!A:A,A11,'Sales Data'!G:G) -> 502979.44 | E11: =C11-D11 -> 480389.71 | F11: =IFERROR(E11/C11,0) -> 0.48851411 | G11: =SUMIF('Sales Data'!A:A,A11,'Sales Data'!I:I) -> 195 | H11: =SUMIF('Sales Data'!A:A,A11,'Sales Data'!J:J) -> 956565.51
A12: Aug | B12: =SUMIF('Sales Data'!A:A,A12,'Sales Data'!D:D) -> 9104 | C12: =SUMIF('Sales Data'!A:A,A12,'Sales Data'!F:F) -> 1172859.5 | D12: =SUMIF('Sales Data'!A:A,A12,'Sales Data'!G:G) -> 611134.61 | E12: =C12-D12 -> 561724.93 | F12: =IFERROR(E12/C12,0) -> 0.47893623 | G12: =SUMIF('Sales Data'!A:A,A12,'Sales Data'!I:I) -> 184 | H12: =SUMIF('Sales Data'!A:A,A12,'Sales Data'!J:J) -> 1149658.2
A13: Sep | B13: =SUMIF('Sales Data'!A:A,A13,'Sales Data'!D:D) -> 8002 | C13: =SUMIF('Sales Data'!A:A,A13,'Sales Data'!F:F) -> 1241687 | D13: =SUMIF('Sales Data'!A:A,A13,'Sales Data'!G:G) -> 656688.74 | E13: =C13-D13 -> 584998.3 | F13: =IFERROR(E13/C13,0) -> 0.47113184 | G13: =SUMIF('Sales Data'!A:A,A13,'Sales Data'!I:I) -> 229 | H13: =SUMIF('Sales Data'!A:A,A13,'Sales Data'!J:J) -> 1205970.3
A14: Oct | B14: =SUMIF('Sales Data'!A:A,A14,'Sales Data'!D:D) -> 9450 | C14: =SUMIF('Sales Data'!A:A,A14,'Sales Data'!F:F) -> 1363939.9 | D14: =SUMIF('Sales Data'!A:A,A14,'Sales Data'!G:G) -> 705350.81 | E14: =C14-D14 -> 658589.06 | F14: =IFERROR(E14/C14,0) -> 0.48285784 | G14: =SUMIF('Sales Data'!A:A,A14,'Sales Data'!I:I) -> 230 | H14: =SUMIF('Sales Data'!A:A,A14,'Sales Data'!J:J) -> 1332309.6
A15: Nov | B15: =SUMIF('Sales Data'!A:A,A15,'Sales Data'!D:D) -> 8743 | C15: =SUMIF('Sales Data'!A:A,A15,'Sales Data'!F:F) -> 1111875.3 | D15: =SUMIF('Sales Data'!A:A,A15,'Sales Data'!G:G) -> 591048.57 | E15: =C15-D15 -> 520826.76 | F15: =IFERROR(E15/C15,0) -> 0.4684219 | G15: =SUMIF('Sales Data'!A:A,A15,'Sales Data'!I:I) -> 178 | H15: =SUMIF('Sales Data'!A:A,A15,'Sales Data'!J:J) -> 1089373.3
A16: Dec | B16: =SUMIF('Sales Data'!A:A,A16,'Sales Data'!D:D) -> 8184 | C16: =SUMIF('Sales Data'!A:A,A16,'Sales Data'!F:F) -> 967790.2 | D16: =SUMIF('Sales Data'!A:A,A16,'Sales Data'!G:G) -> 485877.89 | E16: =C16-D16 -> 481912.31 | F16: =IFERROR(E16/C16,0) -> 0.49795122 | G16: =SUMIF('Sales Data'!A:A,A16,'Sales Data'!I:I) -> 201 | H16: =SUMIF('Sales Data'!A:A,A16,'Sales Data'!J:J) -> 946626.89
A17: TOTAL | B17: =SUM(B5:B16) -> 99864 | C17: =SUM(C5:C16) -> 13303526 | D17: =SUM(D5:D16) -> 7034795.9 | E17: =SUM(E5:E16) -> 6268729.8 | F17: =IFERROR(E17/C17,0) -> 0.47120815 | G17: =SUM(G5:G16) -> 2357 | H17: =SUM(H5:H16) -> 13000787

Sheet Category Analysis
A1: 📦 SALES PERFORMANCE BY CATEGORY — 2024
A2: Category breakdown of revenue, profit and returns
A4: Category | B4: Total Units | C4: Total Revenue ($) | D4: Gross Profit ($) | E4: GP Margin % | F4: Returns | G4: Net Revenue ($)
A5: Electronics | B5: =SUMIF('Sales Data'!B:B,A5,'Sales Data'!D:D) -> 17491 | C5: =SUMIF('Sales Data'!B:B,A5,'Sales Data'!F:F) -> 2011117.6 | D5: =SUMIF('Sales Data'!B:B,A5,'Sales Data'!H:H) -> 951192.34 | E5: =IFERROR(D5/C5,0) -> 0.47296703 | F5: =SUMIF('Sales Data'!B:B,A5,'Sales Data'!I:I) -> 480 | G5: =SUMIF('Sales Data'!B:B,A5,'Sales Data'!J:J) -> 1955298.5
A6: Clothing | B6: =SUMIF('Sales Data'!B:B,A6,'Sales Data'!D:D) -> 17145 | C6: =SUMIF('Sales Data'!B:B,A6,'Sales Data'!F:F) -> 2351492.5 | D6: =SUMIF('Sales Data'!B:B,A6,'Sales Data'!H:H) -> 1120352.7 | E6: =IFERROR(D6/C6,0) -> 0.47644326 | F6: =SUMIF('Sales Data'!B:B,A6,'Sales Data'!I:I) -> 370 | G6: =SUMIF('Sales Data'!B:B,A6,'Sales Data'!J:J) -> 2299739.6
A7: Home & Garden | B7: =SUMIF('Sales Data'!B:B,A7,'Sales Data'!D:D) -> 16044 | C7: =SUMIF('Sales Data'!B:B,A7,'Sales Data'!F:F) -> 1979342.1 | D7: =SUMIF('Sales Data'!B:B,A7,'Sales Data'!H:H) -> 919029.55 | E7: =IFERROR(D7/C7,0) -> 0.46431063 | F7: =SUMIF('Sales Data'!B:B,A7,'Sales Data'!I:I) -> 359 | G7: =SUMIF('Sales Data'!B:B,A7,'Sales Data'!J:J) -> 1935774.1
A8: Sports | B8: =SUMIF('Sales Data'!B:B,A8,'Sales Data'!D:D) -> 17252 | C8: =SUMIF('Sales Data'!B:B,A8,'Sales Data'!F:F) -> 2521901.5 | D8: =SUMIF('Sales Data'!B:B,A8,'Sales Data'!H:H) -> 1199146.4 | E8: =IFERROR(D8/C8,0) -> 0.47549294 | F8: =SUMIF('Sales Data'!B:B,A8,'Sales Data'!I:I) -> 359 | G8: =SUMIF('Sales Data'!B:B,A8,'Sales Data'!J:J) -> 2470660
A9: Beauty | B9: =SUMIF('Sales Data'!B:B,A9,'Sales Data'!D:D) -> 16105 | C9: =SUMIF('Sales Data'!B:B,A9,'Sales Data'!F:F) -> 2200077 | D9: =SUMIF('Sales Data'!B:B,A9,'Sales Data'!H:H) -> 1024688.7 | E9: =IFERROR(D9/C9,0) -> 0.46575129 | F9: =SUMIF('Sales Data'!B:B,A9,'Sales Data'!I:I) -> 439 | G9: =SUMIF('Sales Data'!B:B,A9,'Sales Data'!J:J) -> 2144563
A10: Books | B10: =SUMIF('Sales Data'!B:B,A10,'Sales Data'!D:D) -> 15827 | C10: =SUMIF('Sales Data'!B:B,A10,'Sales Data'!F:F) -> 2239595.1 | D10: =SUMIF('Sales Data'!B:B,A10,'Sales Data'!H:H) -> 1054320.1 | E10: =IFERROR(D10/C10,0) -> 0.47076372 | F10: =SUMIF('Sales Data'!B:B,A10,'Sales Data'!I:I) -> 350 | G10: =SUMIF('Sales Data'!B:B,A10,'Sales Data'!J:J) -> 2194751.8
A11: TOTAL | B11: =SUM(B5:B10) -> 99864 | C11: =SUM(C5:C10) -> 13303526 | D11: =SUM(D5:D10) -> 6268729.8 | E11: =IFERROR(D11/C11,0) -> 0.47120815 | F11: =SUM(F5:F10) -> 2357 | G11: =SUM(G5:G10) -> 13000787

Sheet Region Analysis
A1: 🌍 SALES PERFORMANCE BY REGION — 2024
A2: Regional breakdown to identify top-performing markets
A4: Region | B4: Total Units | C4: Total Revenue ($) | D4: Gross Profit ($) | E4: GP Margin % | F4: Net Revenue ($)
A5: North | B5: =SUMIF('Sales Data'!C:C,A5,'Sales Data'!D:D) -> 19863 | C5: =SUMIF('Sales Data'!C:C,A5,'Sales Data'!F:F) -> 2603868.8 | D5: =SUMIF('Sales Data'!C:C,A5,'Sales Data'!H:H) -> 1242799 | E5: =IFERROR(D5/C5,0) -> 0.47728941 | F5: =SUMIF('Sales Data'!C:C,A5,'Sales Data'!J:J) -> 2530773.7
A6: South | B6: =SUMIF('Sales Data'!C:C,A6,'Sales Data'!D:D) -> 21098 | C6: =SUMIF('Sales Data'!C:C,A6,'Sales Data'!F:F) -> 2512433 | D6: =SUMIF('Sales Data'!C:C,A6,'Sales Data'!H:H) -> 1187111.8 | E6: =IFERROR(D6/C6,0) -> 0.4724949 | F6: =SUMIF('Sales Data'!C:C,A6,'Sales Data'!J:J) -> 2457836.6
A7: East | B7: =SUMIF('Sales Data'!C:C,A7,'Sales Data'!D:D) -> 21063 | C7: =SUMIF('Sales Data'!C:C,A7,'Sales Data'!F:F) -> 3028926.5 | D7: =SUMIF('Sales Data'!C:C,A7,'Sales Data'!H:H) -> 1402507.1 | E7: =IFERROR(D7/C7,0) -> 0.46303768 | F7: =SUMIF('Sales Data'!C:C,A7,'Sales Data'!J:J) -> 2963736.9
A8: West | B8: =SUMIF('Sales Data'!C:C,A8,'Sales Data'!D:D) -> 17835 | C8: =SUMIF('Sales Data'!C:C,A8,'Sales Data'!F:F) -> 2318744.8 | D8: =SUMIF('Sales Data'!C:C,A8,'Sales Data'!H:H) -> 1106432.4 | E8: =IFERROR(D8/C8,0) -> 0.47716871 | F8: =SUMIF('Sales Data'!C:C,A8,'Sales Data'!J:J) -> 2272627
A9: Central | B9: =SUMIF('Sales Data'!C:C,A9,'Sales Data'!D:D) -> 20005 | C9: =SUMIF('Sales Data'!C:C,A9,'Sales Data'!F:F) -> 2839552.6 | D9: =SUMIF('Sales Data'!C:C,A9,'Sales Data'!H:H) -> 1329879.4 | E9: =IFERROR(D9/C9,0) -> 0.46834119 | F9: =SUMIF('Sales Data'!C:C,A9,'Sales Data'!J:J) -> 2775812.9
A10: TOTAL | B10: =SUM(B5:B9) -> 99864 | C10: =SUM(C5:C9) -> 13303526 | D10: =SUM(D5:D9) -> 6268729.8 | E10: =IFERROR(D10/C10,0) -> 0.47120815 | F10: =SUM(F5:F9) -> 13000787
