Workbook

Sheet Research Dashboard
A1: 🔬 ECONOMIC RESEARCH DATA ANALYSIS DASHBOARD | 10 COUNTRIES | 2021-2024
A2: Prepared by: Omer Abdalla | Data Analyst & Banking Professional | June 2026
A4: Total Records | C4: Countries Covered | E4: Years Analyzed | G4: Avg GDP Growth | I4: Total FDI ($M) | K4: Avg HDI Score
A5: =COUNTA('Research Data'!A2:A321) -> 320 | C5: =COUNTA('Country Summary'!A5:A14) -> 10 | E5: =COUNTA('Year Trend Analysis'!A5:A8) -> 4 | G5: =AVERAGE('Research Data'!D2:D321) -> 3.0618125 | I5: =SUM('Research Data'!G2:G321) -> 303289.7 | K5: =AVERAGE('Research Data'!J2:J321) -> 0.67288125
A8: TOP COUNTRIES — FDI & INVESTMENT SCORE | G8: YEAR-ON-YEAR ECONOMIC TRENDS
A9: Country | B9: Avg GDP % | C9: Total FDI ($M) | D9: Avg HDI | E9: Inv. Score | G9: Year | H9: Avg GDP % | I9: Avg Inflation % | J9: Avg HDI
A10: ='Country Summary'!A5 -> Sudan | B10: ='Country Summary'!B5 -> 3.4171875 | C10: ='Country Summary'!E5 -> 30675.6 | D10: ='Country Summary'!F5 -> 0.68109375 | E10: ='Country Summary'!G5 -> 2.269375 | G10: ='Year Trend Analysis'!A5 -> 2021 | H10: ='Year Trend Analysis'!B5 -> 3.379 | I10: ='Year Trend Analysis'!C5 -> 9.177875 | J10: ='Year Trend Analysis'!F5 -> 0.671775
A11: ='Country Summary'!A6 -> Egypt | B11: ='Country Summary'!B6 -> 3.0453125 | C11: ='Country Summary'!E6 -> 31367 | D11: ='Country Summary'!F6 -> 0.6533125 | E11: ='Country Summary'!G6 -> 2.3525 | G11: ='Year Trend Analysis'!A6 -> 2022 | H11: ='Year Trend Analysis'!B6 -> 2.443375 | I11: ='Year Trend Analysis'!C6 -> 10.085875 | J11: ='Year Trend Analysis'!F6 -> 0.6785
A12: ='Country Summary'!A7 -> UAE | B12: ='Country Summary'!B7 -> 2.2821875 | C12: ='Country Summary'!E7 -> 26075.4 | D12: ='Country Summary'!F7 -> 0.69434375 | E12: ='Country Summary'!G7 -> 1.2340625 | G12: ='Year Trend Analysis'!A7 -> 2023 | H12: ='Year Trend Analysis'!B7 -> 3.450125 | I12: ='Year Trend Analysis'!C7 -> 10.6305 | J12: ='Year Trend Analysis'!F7 -> 0.677075
A13: ='Country Summary'!A8 -> Saudi Arabia | B13: ='Country Summary'!B8 -> 2.788125 | C13: ='Country Summary'!E8 -> 29641.6 | D13: ='Country Summary'!F8 -> 0.66546875 | E13: ='Country Summary'!G8 -> 1.9128125 | G13: ='Year Trend Analysis'!A8 -> 2024 | H13: ='Year Trend Analysis'!B8 -> 2.97475 | I13: ='Year Trend Analysis'!C8 -> 8.8585 | J13: ='Year Trend Analysis'!F8 -> 0.664175
A14: ='Country Summary'!A9 -> Jordan | B14: ='Country Summary'!B9 -> 3.119375 | C14: ='Country Summary'!E9 -> 35085.2 | D14: ='Country Summary'!F9 -> 0.65640625 | E14: ='Country Summary'!G9 -> 2.445625
A15: ='Country Summary'!A10 -> Morocco | B15: ='Country Summary'!B10 -> 3.2140625 | C15: ='Country Summary'!E10 -> 24086.6 | D15: ='Country Summary'!F10 -> 0.63953125 | E15: ='Country Summary'!G10 -> 2.2625
A16: ='Country Summary'!A11 -> Tunisia | B16: ='Country Summary'!B11 -> 3.261875 | C16: ='Country Summary'!E11 -> 31805 | D16: ='Country Summary'!F11 -> 0.67715625 | E16: ='Country Summary'!G11 -> 1.826875
A17: ='Country Summary'!A12 -> Algeria | B17: ='Country Summary'!B12 -> 3.646875 | C17: ='Country Summary'!E12 -> 28051 | D17: ='Country Summary'!F12 -> 0.69071875 | E17: ='Country Summary'!G12 -> 2.585
A18: ='Country Summary'!A13 -> Kuwait | B18: ='Country Summary'!B13 -> 3.563125 | C18: ='Country Summary'!E13 -> 30628.8 | D18: ='Country Summary'!F13 -> 0.69575 | E18: ='Country Summary'!G13 -> 2.498125
A19: ='Country Summary'!A14 -> Qatar | B19: ='Country Summary'!B14 -> 2.28 | C19: ='Country Summary'!E14 -> 35873.5 | D19: ='Country Summary'!F14 -> 0.67503125 | E19: ='Country Summary'!G14 -> 1.5965625
A30: © 2026 Omer Abdalla | Research Data Analysis | github.com/3mor9411

Sheet Research Data
A1: Country | B1: Sector | C1: Year | D1: GDP Growth (%) | E1: Inflation (%) | F1: Unemployment (%) | G1: FDI Inflow ($M) | H1: Trade Balance ($M) | I1: Public Debt (% GDP) | J1: HDI Score | K1: Investment Score | L1: Risk Rating | M1: Data Quality
A2: Sudan | B2: Banking | C2: 2021 | D2: 2.04 | E2: 5.2 | F2: 6.4 | G2: 534.4 | H2: 1019.8 | I2: 37.6 | J2: 0.615 | K2: 2.73 | L2: Low Risk | M2: Excellent
A3: Sudan | B3: Banking | C3: 2022 | D3: 7.38 | E3: 9.83 | F3: 11.01 | G3: 1245.8 | H3: -66.6 | I3: 83.1 | J3: 0.611 | K3: 4.36 | L3: Low Risk | M3: Poor
A4: Sudan | B4: Banking | C4: 2023 | D4: 6.61 | E4: 5.4 | F4: 11.77 | G4: 399.1 | H4: 633.8 | I4: 25.8 | J4: 0.758 | K4: 4.88 | L4: Low Risk | M4: Excellent
A5: Sudan | B5: Banking | C5: 2024 | D5: 2.69 | E5: 8.44 | F5: 8.12 | G5: 64.9 | H5: -92.5 | I5: 89.3 | J5: 0.68 | K5: 1.85 | L5: Low Risk | M5: Poor
A6: Sudan | B6: Healthcare | C6: 2021 | D6: 3.19 | E6: 5.17 | F6: 11.79 | G6: 150.1 | H6: -241.7 | I6: 86.7 | J6: 0.758 | K6: 3.12 | L6: Low Risk | M6: Poor
A7: Sudan | B7: Healthcare | C7: 2022 | D7: 3.95 | E7: 17.73 | F7: 20.93 | G7: 1337.6 | H7: -425.9 | I7: 21.6 | J7: 0.654 | K7: 0.32 | L7: High Risk | M7: Poor
A8: Sudan | B8: Healthcare | C8: 2023 | D8: -1.19 | E8: 8.81 | F8: 4.63 | G8: 654.1 | H8: -488.7 | I8: 43.1 | J8: 0.675 | K8: 0.09 | L8: Low Risk | M8: Good
A9: Sudan | B9: Healthcare | C9: 2024 | D9: 7 | E9: 17.58 | F9: 15.17 | G9: 913.8 | H9: 590.9 | I9: 77.8 | J9: 0.504 | K9: 1.68 | L9: High Risk | M9: Poor
A10: Sudan | B10: Education | C10: 2021 | D10: 7.22 | E10: 4.09 | F10: 19.41 | G10: 1219.4 | H10: 994.4 | I10: 62.6 | J10: 0.626 | K10: 5.99 | L10: Low Risk | M10: Excellent
A11: Sudan | B11: Education | C11: 2022 | D11: -0.81 | E11: 6.74 | F11: 21.83 | G11: 849.3 | H11: 1348.3 | I11: 81.6 | J11: 0.587 | K11: 1 | L11: Low Risk | M11: Poor
A12: Sudan | B12: Education | C12: 2023 | D12: 5.98 | E12: 15.54 | F12: 5.23 | G12: 1653.6 | H12: -128.1 | I12: 25.1 | J12: 0.574 | K12: 2.15 | L12: High Risk | M12: Excellent
A13: Sudan | B13: Education | C13: 2024 | D13: 1.37 | E13: 8.03 | F13: 9.4 | G13: 1634.1 | H13: 271.9 | I13: 77 | J13: 0.68 | K13: 2.09 | L13: Low Risk | M13: Good
... A321: Qatar | B321: Retail | C321: 2024 | D321: 2.47 | E321: 16.05 | F321: 12.23 | G321: 1394.3 | H321: 551 | I321: 43.2 | J321: 0.472 | K321: 0.12 | L321: High Risk | M321: Fair

Sheet Country Summary
A1: 🌍 ECONOMIC INDICATORS BY COUNTRY — RESEARCH SUMMARY 2021-2024
A2: Average economic indicators across all sectors and years | Analyst: Omer Abdalla
A4: Country | B4: Avg GDP Growth | C4: Avg Inflation | D4: Avg Unemployment | E4: Total FDI ($M) | F4: Avg HDI | G4: Avg Investment Score | H4: Data Points
A5: Sudan | B5: =AVERAGEIF('Research Data'!A:A,A5,'Research Data'!D:D) -> 3.4171875 | C5: =AVERAGEIF('Research Data'!A:A,A5,'Research Data'!E:E) -> 9.7259375 | D5: =AVERAGEIF('Research Data'!A:A,A5,'Research Data'!F:F) -> 13.479688 | E5: =SUMIF('Research Data'!A:A,A5,'Research Data'!G:G) -> 30675.6 | F5: =AVERAGEIF('Research Data'!A:A,A5,'Research Data'!J:J) -> 0.68109375 | G5: =AVERAGEIF('Research Data'!A:A,A5,'Research Data'!K:K) -> 2.269375 | H5: =COUNTIF('Research Data'!A:A,A5) -> 32
A6: Egypt | B6: =AVERAGEIF('Research Data'!A:A,A6,'Research Data'!D:D) -> 3.0453125 | C6: =AVERAGEIF('Research Data'!A:A,A6,'Research Data'!E:E) -> 8.8671875 | D6: =AVERAGEIF('Research Data'!A:A,A6,'Research Data'!F:F) -> 11.04875 | E6: =SUMIF('Research Data'!A:A,A6,'Research Data'!G:G) -> 31367 | F6: =AVERAGEIF('Research Data'!A:A,A6,'Research Data'!J:J) -> 0.6533125 | G6: =AVERAGEIF('Research Data'!A:A,A6,'Research Data'!K:K) -> 2.3525 | H6: =COUNTIF('Research Data'!A:A,A6) -> 32
A7: UAE | B7: =AVERAGEIF('Research Data'!A:A,A7,'Research Data'!D:D) -> 2.2821875 | C7: =AVERAGEIF('Research Data'!A:A,A7,'Research Data'!E:E) -> 11.048125 | D7: =AVERAGEIF('Research Data'!A:A,A7,'Research Data'!F:F) -> 11.225 | E7: =SUMIF('Research Data'!A:A,A7,'Research Data'!G:G) -> 26075.4 | F7: =AVERAGEIF('Research Data'!A:A,A7,'Research Data'!J:J) -> 0.69434375 | G7: =AVERAGEIF('Research Data'!A:A,A7,'Research Data'!K:K) -> 1.2340625 | H7: =COUNTIF('Research Data'!A:A,A7) -> 32
A8: Saudi Arabia | B8: =AVERAGEIF('Research Data'!A:A,A8,'Research Data'!D:D) -> 2.788125 | C8: =AVERAGEIF('Research Data'!A:A,A8,'Research Data'!E:E) -> 9.8175 | D8: =AVERAGEIF('Research Data'!A:A,A8,'Research Data'!F:F) -> 12.665938 | E8: =SUMIF('Research Data'!A:A,A8,'Research Data'!G:G) -> 29641.6 | F8: =AVERAGEIF('Research Data'!A:A,A8,'Research Data'!J:J) -> 0.66546875 | G8: =AVERAGEIF('Research Data'!A:A,A8,'Research Data'!K:K) -> 1.9128125 | H8: =COUNTIF('Research Data'!A:A,A8) -> 32
A9: Jordan | B9: =AVERAGEIF('Research Data'!A:A,A9,'Research Data'!D:D) -> 3.119375 | C9: =AVERAGEIF('Research Data'!A:A,A9,'Research Data'!E:E) -> 8.879375 | D9: =AVERAGEIF('Research Data'!A:A,A9,'Research Data'!F:F) -> 11.739688 | E9: =SUMIF('Research Data'!A:A,A9,'Research Data'!G:G) -> 35085.2 | F9: =AVERAGEIF('Research Data'!A:A,A9,'Research Data'!J:J) -> 0.65640625 | G9: =AVERAGEIF('Research Data'!A:A,A9,'Research Data'!K:K) -> 2.445625 | H9: =COUNTIF('Research Data'!A:A,A9) -> 32
A10: Morocco | B10: =AVERAGEIF('Research Data'!A:A,A10,'Research Data'!D:D) -> 3.2140625 | C10: =AVERAGEIF('Research Data'!A:A,A10,'Research Data'!E:E) -> 9.070625 | D10: =AVERAGEIF('Research Data'!A:A,A10,'Research Data'!F:F) -> 12.94625 | E10: =SUMIF('Research Data'!A:A,A10,'Research Data'!G:G) -> 24086.6 | F10: =AVERAGEIF('Research Data'!A:A,A10,'Research Data'!J:J) -> 0.63953125 | G10: =AVERAGEIF('Research Data'!A:A,A10,'Research Data'!K:K) -> 2.2625 | H10: =COUNTIF('Research Data'!A:A,A10) -> 32
A11: Tunisia | B11: =AVERAGEIF('Research Data'!A:A,A11,'Research Data'!D:D) -> 3.261875 | C11: =AVERAGEIF('Research Data'!A:A,A11,'Research Data'!E:E) -> 11.000937 | D11: =AVERAGEIF('Research Data'!A:A,A11,'Research Data'!F:F) -> 11.396875 | E11: =SUMIF('Research Data'!A:A,A11,'Research Data'!G:G) -> 31805 | F11: =AVERAGEIF('Research Data'!A:A,A11,'Research Data'!J:J) -> 0.67715625 | G11: =AVERAGEIF('Research Data'!A:A,A11,'Research Data'!K:K) -> 1.826875 | H11: =COUNTIF('Research Data'!A:A,A11) -> 32
A12: Algeria | B12: =AVERAGEIF('Research Data'!A:A,A12,'Research Data'!D:D) -> 3.646875 | C12: =AVERAGEIF('Research Data'!A:A,A12,'Research Data'!E:E) -> 8.920625 | D12: =AVERAGEIF('Research Data'!A:A,A12,'Research Data'!F:F) -> 12.05 | E12: =SUMIF('Research Data'!A:A,A12,'Research Data'!G:G) -> 28051 | F12: =AVERAGEIF('Research Data'!A:A,A12,'Research Data'!J:J) -> 0.69071875 | G12: =AVERAGEIF('Research Data'!A:A,A12,'Research Data'!K:K) -> 2.585 | H12: =COUNTIF('Research Data'!A:A,A12) -> 32
A13: Kuwait | B13: =AVERAGEIF('Research Data'!A:A,A13,'Research Data'!D:D) -> 3.563125 | C13: =AVERAGEIF('Research Data'!A:A,A13,'Research Data'!E:E) -> 9.208125 | D13: =AVERAGEIF('Research Data'!A:A,A13,'Research Data'!F:F) -> 11.581875 | E13: =SUMIF('Research Data'!A:A,A13,'Research Data'!G:G) -> 30628.8 | F13: =AVERAGEIF('Research Data'!A:A,A13,'Research Data'!J:J) -> 0.69575 | G13: =AVERAGEIF('Research Data'!A:A,A13,'Research Data'!K:K) -> 2.498125 | H13: =COUNTIF('Research Data'!A:A,A13) -> 32
A14: Qatar | B14: =AVERAGEIF('Research Data'!A:A,A14,'Research Data'!D:D) -> 2.28 | C14: =AVERAGEIF('Research Data'!A:A,A14,'Research Data'!E:E) -> 10.343438 | D14: =AVERAGEIF('Research Data'!A:A,A14,'Research Data'!F:F) -> 12.133125 | E14: =SUMIF('Research Data'!A:A,A14,'Research Data'!G:G) -> 35873.5 | F14: =AVERAGEIF('Research Data'!A:A,A14,'Research Data'!J:J) -> 0.67503125 | G14: =AVERAGEIF('Research Data'!A:A,A14,'Research Data'!K:K) -> 1.5965625 | H14: =COUNTIF('Research Data'!A:A,A14) -> 32
A15: AVERAGE/TOTAL | B15: =AVERAGE(B5:B14) -> 3.0618125 | C15: =AVERAGE(C5:C14) -> 9.6881875 | D15: =AVERAGE(D5:D14) -> 12.026719 | E15: =SUM(E5:E14) -> 303289.7 | F15: =AVERAGE(F5:F14) -> 0.67288125 | G15: =AVERAGE(G5:G14) -> 2.0983438 | H15: =SUM(H5:H14) -> 320

Sheet Year Trend Analysis
A1: 📈 YEAR-ON-YEAR TREND ANALYSIS — 2021 TO 2024
A2: Tracking macroeconomic indicators over 4 years across all countries
A4: Year | B4: Avg GDP Growth | C4: Avg Inflation | D4: Avg Unemployment | E4: Total FDI ($M) | F4: Avg HDI | G4: Total Data Points | I4: YEAR-ON-YEAR CHANGE ANALYSIS
A5: 2021 | B5: =AVERAGEIF('Research Data'!C:C,A5,'Research Data'!D:D) -> 3.379 | C5: =AVERAGEIF('Research Data'!C:C,A5,'Research Data'!E:E) -> 9.177875 | D5: =AVERAGEIF('Research Data'!C:C,A5,'Research Data'!F:F) -> 11.801 | E5: =SUMIF('Research Data'!C:C,A5,'Research Data'!G:G) -> 73184.8 | F5: =AVERAGEIF('Research Data'!C:C,A5,'Research Data'!J:J) -> 0.671775 | G5: =COUNTIF('Research Data'!C:C,A5) -> 80 | I5: Metric | J5: 2022 vs 2021 | K5: 2023 vs 2022 | L5: 2024 vs 2023
A6: 2022 | B6: =AVERAGEIF('Research Data'!C:C,A6,'Research Data'!D:D) -> 2.443375 | C6: =AVERAGEIF('Research Data'!C:C,A6,'Research Data'!E:E) -> 10.085875 | D6: =AVERAGEIF('Research Data'!C:C,A6,'Research Data'!F:F) -> 11.97775 | E6: =SUMIF('Research Data'!C:C,A6,'Research Data'!G:G) -> 80837.1 | F6: =AVERAGEIF('Research Data'!C:C,A6,'Research Data'!J:J) -> 0.6785 | G6: =COUNTIF('Research Data'!C:C,A6) -> 80 | I6: GDP Growth | J6: =IFERROR(B6-B5,"-") -> -0.935625 | K6: =IFERROR(B7-B6,"-") -> 1.00675 | L6: =IFERROR(B8-B7,"-") -> -0.475375
A7: 2023 | B7: =AVERAGEIF('Research Data'!C:C,A7,'Research Data'!D:D) -> 3.450125 | C7: =AVERAGEIF('Research Data'!C:C,A7,'Research Data'!E:E) -> 10.6305 | D7: =AVERAGEIF('Research Data'!C:C,A7,'Research Data'!F:F) -> 12.30525 | E7: =SUMIF('Research Data'!C:C,A7,'Research Data'!G:G) -> 72922 | F7: =AVERAGEIF('Research Data'!C:C,A7,'Research Data'!J:J) -> 0.677075 | G7: =COUNTIF('Research Data'!C:C,A7) -> 80 | I7: Inflation | J7: =IFERROR(C6-C5,"-") -> 0.908 | K7: =IFERROR(C7-C6,"-") -> 0.544625 | L7: =IFERROR(C8-C7,"-") -> -1.772
A8: 2024 | B8: =AVERAGEIF('Research Data'!C:C,A8,'Research Data'!D:D) -> 2.97475 | C8: =AVERAGEIF('Research Data'!C:C,A8,'Research Data'!E:E) -> 8.8585 | D8: =AVERAGEIF('Research Data'!C:C,A8,'Research Data'!F:F) -> 12.022875 | E8: =SUMIF('Research Data'!C:C,A8,'Research Data'!G:G) -> 76345.8 | F8: =AVERAGEIF('Research Data'!C:C,A8,'Research Data'!J:J) -> 0.664175 | G8: =COUNTIF('Research Data'!C:C,A8) -> 80 | I8: Unemployment | J8: =IFERROR(D6-D5,"-") -> 0.17675 | K8: =IFERROR(D7-D6,"-") -> 0.3275 | L8: =IFERROR(D8-D7,"-") -> -0.282375
I9: HDI | J9: =IFERROR(F6-F5,"-") -> 0.006725 | K9: =IFERROR(F7-F6,"-") -> -0.001425 | L9: =IFERROR(F8-F7,"-") -> -0.0129

Sheet Data Quality Report
A1: 🔍 DATA QUALITY & COMPLETENESS REPORT
A2: Assessing data completeness, accuracy ratings and coverage by country
A4: Country | B4: Total Records | C4: Excellent | D4: Good | E4: Fair | F4: Poor
A5: Sudan | B5: =COUNTIF('Research Data'!A:A,A5) -> 32 | C5: =COUNTIFS('Research Data'!A:A,A5,'Research Data'!M:M,"Excellent") -> 8 | D5: =COUNTIFS('Research Data'!A:A,A5,'Research Data'!M:M,"Good") -> 7 | E5: =COUNTIFS('Research Data'!A:A,A5,'Research Data'!M:M,"Fair") -> 5 | F5: =COUNTIFS('Research Data'!A:A,A5,'Research Data'!M:M,"Poor") -> 12
A6: Egypt | B6: =COUNTIF('Research Data'!A:A,A6) -> 32 | C6: =COUNTIFS('Research Data'!A:A,A6,'Research Data'!M:M,"Excellent") -> 9 | D6: =COUNTIFS('Research Data'!A:A,A6,'Research Data'!M:M,"Good") -> 11 | E6: =COUNTIFS('Research Data'!A:A,A6,'Research Data'!M:M,"Fair") -> 6 | F6: =COUNTIFS('Research Data'!A:A,A6,'Research Data'!M:M,"Poor") -> 6
A7: UAE | B7: =COUNTIF('Research Data'!A:A,A7) -> 32 | C7: =COUNTIFS('Research Data'!A:A,A7,'Research Data'!M:M,"Excellent") -> 10 | D7: =COUNTIFS('Research Data'!A:A,A7,'Research Data'!M:M,"Good") -> 9 | E7: =COUNTIFS('Research Data'!A:A,A7,'Research Data'!M:M,"Fair") -> 8 | F7: =COUNTIFS('Research Data'!A:A,A7,'Research Data'!M:M,"Poor") -> 5
A8: Saudi Arabia | B8: =COUNTIF('Research Data'!A:A,A8) -> 32 | C8: =COUNTIFS('Research Data'!A:A,A8,'Research Data'!M:M,"Excellent") -> 9 | D8: =COUNTIFS('Research Data'!A:A,A8,'Research Data'!M:M,"Good") -> 10 | E8: =COUNTIFS('Research Data'!A:A,A8,'Research Data'!M:M,"Fair") -> 8 | F8: =COUNTIFS('Research Data'!A:A,A8,'Research Data'!M:M,"Poor") -> 5
A9: Jordan | B9: =COUNTIF('Research Data'!A:A,A9) -> 32 | C9: =COUNTIFS('Research Data'!A:A,A9,'Research Data'!M:M,"Excellent") -> 13 | D9: =COUNTIFS('Research Data'!A:A,A9,'Research Data'!M:M,"Good") -> 5 | E9: =COUNTIFS('Research Data'!A:A,A9,'Research Data'!M:M,"Fair") -> 5 | F9: =COUNTIFS('Research Data'!A:A,A9,'Research Data'!M:M,"Poor") -> 9
A10: Morocco | B10: =COUNTIF('Research Data'!A:A,A10) -> 32 | C10: =COUNTIFS('Research Data'!A:A,A10,'Research Data'!M:M,"Excellent") -> 10 | D10: =COUNTIFS('Research Data'!A:A,A10,'Research Data'!M:M,"Good") -> 8 | E10: =COUNTIFS('Research Data'!A:A,A10,'Research Data'!M:M,"Fair") -> 7 | F10: =COUNTIFS('Research Data'!A:A,A10,'Research Data'!M:M,"Poor") -> 7
A11: Tunisia | B11: =COUNTIF('Research Data'!A:A,A11) -> 32 | C11: =COUNTIFS('Research Data'!A:A,A11,'Research Data'!M:M,"Excellent") -> 10 | D11: =COUNTIFS('Research Data'!A:A,A11,'Research Data'!M:M,"Good") -> 9 | E11: =COUNTIFS('Research Data'!A:A,A11,'Research Data'!M:M,"Fair") -> 6 | F11: =COUNTIFS('Research Data'!A:A,A11,'Research Data'!M:M,"Poor") -> 7
A12: Algeria | B12: =COUNTIF('Research Data'!A:A,A12) -> 32 | C12: =COUNTIFS('Research Data'!A:A,A12,'Research Data'!M:M,"Excellent") -> 7 | D12: =COUNTIFS('Research Data'!A:A,A12,'Research Data'!M:M,"Good") -> 10 | E12: =COUNTIFS('Research Data'!A:A,A12,'Research Data'!M:M,"Fair") -> 6 | F12: =COUNTIFS('Research Data'!A:A,A12,'Research Data'!M:M,"Poor") -> 9
A13: Kuwait | B13: =COUNTIF('Research Data'!A:A,A13) -> 32 | C13: =COUNTIFS('Research Data'!A:A,A13,'Research Data'!M:M,"Excellent") -> 8 | D13: =COUNTIFS('Research Data'!A:A,A13,'Research Data'!M:M,"Good") -> 8 | E13: =COUNTIFS('Research Data'!A:A,A13,'Research Data'!M:M,"Fair") -> 10 | F13: =COUNTIFS('Research Data'!A:A,A13,'Research Data'!M:M,"Poor") -> 6
A14: Qatar | B14: =COUNTIF('Research Data'!A:A,A14) -> 32 | C14: =COUNTIFS('Research Data'!A:A,A14,'Research Data'!M:M,"Excellent") -> 9 | D14: =COUNTIFS('Research Data'!A:A,A14,'Research Data'!M:M,"Good") -> 4 | E14: =COUNTIFS('Research Data'!A:A,A14,'Research Data'!M:M,"Fair") -> 8 | F14: =COUNTIFS('Research Data'!A:A,A14,'Research Data'!M:M,"Poor") -> 11
